factor_table/__init__.py
factor_table/conf/__init__.py
factor_table/conf/config.py
factor_table/conf/config.yml
factor_table/conf/logger.py
factor_table/core/FactorCreator.py
factor_table/core/FactorPool.py
factor_table/core/Factors.py
factor_table/core/__init__.py
factor_table/core/factortable.py
factor_table/engine/FactorDataFrame.py
factor_table/engine/FactorH5.py
factor_table/engine/FactorSQLClickHouse.py
factor_table/engine/FactorSQLMySQL.py
factor_table/engine/__init__.py
factor_table/helper/FactorTools.py
factor_table/helper/__init__.py
factor_table/helper/transform_dt_format.py
factor_table/utils/__init__.py
factor_table/utils/boost_up.py
factor_table/utils/cached_property.py
factor_table/utils/check_file_type.py
factor_table/utils/chunk.py
factor_table/utils/file_cache.py
factor_table/utils/lazy_load.py
factor_table/utils/logger.py
factor_table/utils/parse_rfc_1738_args.py
factor_table/utils/process_bar.py
factor_table/utils/singleton.py
factor_table/utils/timer.py
factor_table/utils/uuid_generator.py
test/__init__.py
test/config.yml
test/test_Factors.py
test/test_add_factors.py
test/test_factor_pool.py
test/test_factortable.py
factor_table-0.2.3.1.dist-info/METADATA
factor_table-0.2.3.1.dist-info/WHEEL
factor_table-0.2.3.1.dist-info/top_level.txt
factor_table-0.2.3.1.dist-info/RECORD
