Metadata-Version: 2.1
Name: factor-table
Version: 0.2.3.1
Summary: data collection 
Home-page: http://www.github.com/sn0wfree
Author: sn0wfree
Author-email: snowfreedom0815@gmail.com
License: UNKNOWN
Keywords: factor,table,data,dataset
Platform: UNKNOWN
